.gitignore
README
TODO
setup.py
adminish/__init__.py
adminish/config.py
adminish/expand.py
adminish/index.py
adminish/markdown.py
adminish/md.py
adminish/mdx_enhanced_image.py
adminish/resource.py
adminish.egg-info/PKG-INFO
adminish.egg-info/SOURCES.txt
adminish.egg-info/dependency_links.txt
adminish.egg-info/entry_points.txt
adminish.egg-info/not-zip-safe
adminish.egg-info/requires.txt
adminish.egg-info/top_level.txt
adminish/templates/adminish/bare.html
adminish/templates/adminish/categories.html
adminish/templates/adminish/facet.html
adminish/templates/adminish/facets.html
adminish/templates/adminish/item.html
adminish/templates/adminish/items.html
adminish/templates/adminish/main.html
adminish/templates/adminish/new_item.html
adminish/templates/adminish/preview.html
adminish/templates/adminish/root.html
adminish/templates/formish/widgets/CheckboxMultiChoiceTreeCouchDB/widget.html
adminish/templates/formish/widgets/SeqRefTextArea/widget.html
data/admin_user.json
data/model/user.model.yaml
data/model/views.yaml