Metadata-Version: 1.0
Name: adminish
Version: 0.1.3
Summary: Auto web admin system for couchdb and restish
Home-page: http://ish.io
Author: Tim Parkin & Matt Goodall
Author-email: info@timparkin.co.uk
License: UNKNOWN
Platform: UNKNOWN
